ppy_common/__init__.py
ppy_common/ppy_common_helper.py
ppy_common/ppy_data.py
ppy_common/ppy_data_util.py
ppy_common/ppy_date_util.py
ppy_common/ppy_object_helper.py
ppy_common/ppy_url_util.py
ppy_common/ppyc_console_log.py
ppy_common/ppyc_exception.py
ppy_common-0.0.8.dist-info/LICENSE
ppy_common-0.0.8.dist-info/METADATA
ppy_common-0.0.8.dist-info/WHEEL
ppy_common-0.0.8.dist-info/top_level.txt
ppy_common-0.0.8.dist-info/RECORD
