Metadata-Version: 2.1
Name: ppy-common
Version: 0.0.8
Summary: PWeb Python Common is a library which help various common work to do easily
Home-page: https://github.com/banglafighter/ppy-common
Author: Bangla Fighter
Author-email: banglafighter.com@gmail.com
License: Apache 2.0
Platform: any
Classifier: Intended Audience :: Developers
Classifier: License :: OSI Approved :: Apache Software License
Classifier: Programming Language :: Python
License-File: LICENSE
Requires-Dist: click ==8.1.7
Requires-Dist: terminaltables ==3.1.10
